{
  "id": "what-happened-there",
  "archived_at": "2026-04-16T03:56:07Z",
  "legacy": true,
  "metadata": {
    "title": "What Happened There?",
    "artist": "Keiji Haino",
    "codec": "FLAC",
    "num_tracks": 4,
    "duration_human": "35:45",
    "sampling_rate": "44.1kHz"
  },
  "hosts": {
    "archive_org": {
      "url": "https://archive.org/details/1764806612_what_happened_there"
    },
    "pomf2_lain_la": {
      "url": "https://pomf2.lain.la/f/s468ervv.7z"
    },
    "catbox": {
      "url": "https://files.catbox.moe/jbcdqs.7z"
    },
    "fileditch": {
      "url": "https://fileditchfiles.me/file.php?f=/s24/fUHitELNZtkGWqwigSuL.7z"
    }
  }
}