{
  "id": "live-during-war-crimes-3",
  "archived_at": "2026-04-16T03:56:08Z",
  "legacy": true,
  "metadata": {
    "title": "Live During War Crimes #3",
    "artist": "Yellow Swans",
    "codec": "FLAC",
    "num_tracks": 0,
    "duration_human": "Unknown",
    "sampling_rate": "Unknown"
  },
  "hosts": {
    "archive_org": {
      "url": "https://archive.org/details/1754818129_live_during_war_crimes__3"
    },
    "fileditch": {
      "url": "https://fileditchfiles.me/file.php?f=/b56/WjecPOYRpEvsBUVjzUfF.7z"
    },
    "pomf2_lain_la": {
      "url": "https://pomf2.lain.la/f/3rvirac.7z"
    }
  }
}