{
  "id": "neustadt-altstadt",
  "archived_at": "2026-04-16T03:56:08Z",
  "legacy": true,
  "metadata": {
    "title": "Neustadt / Altstadt",
    "artist": "Sarah Davachi",
    "codec": "FLAC",
    "num_tracks": 2,
    "duration_human": "21:07",
    "sampling_rate": "44.1kHz"
  },
  "hosts": {
    "archive_org": {
      "url": "https://archive.org/details/1761591514_neustadt_-_altstadt"
    },
    "fileditch": {
      "url": "https://fileditchfiles.me/file.php?f=/s24/LEiTLUDUZCuRmSnYplx.7z"
    },
    "catbox": {
      "url": "https://files.catbox.moe/0zcuaf.7z"
    },
    "pomf2_lain_la": {
      "url": "https://pomf2.lain.la/f/gb413rlq.7z"
    }
  }
}