{
  "id": "bell-voices-from-lake-my-son",
  "archived_at": "2026-04-16T03:56:08Z",
  "legacy": true,
  "metadata": {
    "title": "Bell Voices from Lake (my Son)",
    "artist": "Zeffon / Argon Beams / Generated Missiân ZFN / Revenence / Serpentmouth (incomplete as of now)",
    "codec": "FLAC",
    "num_tracks": 0,
    "duration_human": "Unknown",
    "sampling_rate": "Unknown"
  },
  "hosts": {
    "archive_org": {
      "url": "https://archive.org/details/1748648381_zeffon_-_bell_voices_from_lake__my_son_"
    },
    "fileditch": {
      "url": "https://fileditchfiles.me/file.php?f=/b54/HsTZTzUvPexPlaxhDWa.7z"
    },
    "pomf2_lain_la": {
      "url": "https://pomf2.lain.la/f/2zk1l2i.7z"
    }
  }
}