{
  "id": "ai-ma-ra",
  "archived_at": "2026-04-16T03:56:07Z",
  "legacy": true,
  "metadata": {
    "title": "Ai Ma Ra",
    "artist": "Arktau Eos",
    "codec": "FLAC",
    "num_tracks": 0,
    "duration_human": "Unknown",
    "sampling_rate": "Unknown"
  },
  "hosts": {
    "archive_org": {
      "url": "https://archive.org/details/1747649298_ai_ma_ra"
    },
    "fileditch": {
      "url": "https://fileditchfiles.me/file.php?f=/s22/CmYxULcgobkOWdKFlSXW.7z"
    },
    "pomf2_lain_la": {
      "url": "https://pomf2.lain.la/f/2zqysd5v.7z"
    }
  }
}