{
  "id": "sleeping-dogs",
  "archived_at": "2026-04-16T03:56:08Z",
  "legacy": true,
  "metadata": {
    "title": "Sleeping Dogs",
    "artist": "Rozz Williams",
    "codec": "MP3",
    "num_tracks": 0,
    "duration_human": "Unknown",
    "sampling_rate": "Unknown"
  },
  "hosts": {
    "archive_org": {
      "url": "https://archive.org/details/1752376383_sleeping_dogs"
    },
    "fileditch": {
      "url": "https://fileditchfiles.me/file.php?f=/s22/ulWAObJrBPquLhCQEYIr.7z"
    },
    "catbox": {
      "url": "https://files.catbox.moe/jg2blg.7z"
    },
    "pomf2_lain_la": {
      "url": "https://pomf2.lain.la/f/im7kfyzd.7z"
    }
  }
}