{
  "id": "nachtmahr",
  "archived_at": "2026-04-16T03:56:08Z",
  "legacy": true,
  "metadata": {
    "title": "Nachtmahr",
    "artist": "Meret Becker",
    "codec": "MP3",
    "num_tracks": 0,
    "duration_human": "Unknown",
    "sampling_rate": "Unknown"
  },
  "hosts": {
    "archive_org": {
      "url": "https://archive.org/details/1752300516_nachtmahr"
    },
    "fileditch": {
      "url": "https://fileditchfiles.me/file.php?f=/s22/QtitmWiwBaawyDACGwAx.7z"
    },
    "catbox": {
      "url": "https://files.catbox.moe/n40zo6.7z"
    },
    "pomf2_lain_la": {
      "url": "https://pomf2.lain.la/f/i89ry8ll.7z"
    }
  }
}