{
  "id": "computer-facepure-being",
  "archived_at": "2026-04-16T03:56:08Z",
  "legacy": true,
  "metadata": {
    "title": "Computer Face//Pure Being",
    "artist": "Flying Lotus",
    "codec": "FLAC",
    "num_tracks": 0,
    "duration_human": "Unknown",
    "sampling_rate": "Unknown"
  },
  "hosts": {
    "archive_org": {
      "url": "https://archive.org/details/1757191510_computer_face_-_-_pure_being"
    },
    "fileditch": {
      "url": "https://fileditchfiles.me/file.php?f=/s24/FZzvubZzBVJwWawoKdb.7z"
    },
    "catbox": {
      "url": "https://files.catbox.moe/k9dq0l.7z"
    },
    "pomf2_lain_la": {
      "url": "https://pomf2.lain.la/f/9at1lm02.7z"
    }
  }
}