{
  "id": "deus-lhe-paguecitacao-rap-p-agatha-citacao-divida-historica",
  "archived_at": "2026-04-16T03:56:08Z",
  "legacy": true,
  "metadata": {
    "title": "Deus lhe Pague/Citação: Rap (P) Agatha /Citação: Dívida Histórica",
    "artist": "Metá Metá",
    "codec": "FLAC",
    "num_tracks": 0,
    "duration_human": "Unknown",
    "sampling_rate": "Unknown"
  },
  "hosts": {
    "archive_org": {
      "url": "https://archive.org/details/1758595920_deus_lhe_pague_-_cita__o_rap__p__agatha_-_cita__o_"
    },
    "fileditch": {
      "url": "https://fileditchfiles.me/file.php?f=/s24/aFzwfnTLHYDzWQFELzeF.7z"
    },
    "catbox": {
      "url": "https://files.catbox.moe/aa6a09.7z"
    },
    "pomf2_lain_la": {
      "url": "https://pomf2.lain.la/f/g9ysrfsz.7z"
    }
  }
}