{
  "id": "axe-phoebus-aureo",
  "archived_at": "2026-04-16T03:56:07Z",
  "legacy": true,
  "metadata": {
    "title": "Axe Phoebus Aureo",
    "artist": "Mitsuru Tabata",
    "codec": "MP3",
    "num_tracks": 2,
    "duration_human": "41:02",
    "sampling_rate": "44.1kHz"
  },
  "hosts": {
    "archive_org": {
      "url": "https://archive.org/details/1765041303_axe_phoebus_aureo"
    },
    "pomf2_lain_la": {
      "url": "https://pomf2.lain.la/f/67yhwjrp.7z"
    },
    "catbox": {
      "url": "https://files.catbox.moe/61hao3.7z"
    },
    "fileditch": {
      "url": "https://fileditchfiles.me/file.php?f=/s24/pUlvyOADtzJnPcXVfRir.7z"
    }
  }
}