{
  "id": "rivers-shores",
  "archived_at": "2026-04-16T03:56:07Z",
  "legacy": true,
  "metadata": {
    "title": "Rivers & Shores",
    "artist": "Black Hill",
    "codec": "FLAC",
    "num_tracks": 16,
    "duration_human": "38:32",
    "sampling_rate": "44.1kHz"
  },
  "hosts": {
    "archive_org": {
      "url": "https://archive.org/details/1760744555_rivers___shores"
    },
    "fileditch": {
      "url": "https://fileditchfiles.me/file.php?f=/s24/LFnDcsjfczBLLGIRcIHV.7z"
    },
    "catbox": {
      "url": "https://files.catbox.moe/wgcklh.7z"
    },
    "pomf2_lain_la": {
      "url": "https://pomf2.lain.la/f/rjb6drm9.7z"
    }
  }
}