{
  "id": "unreleased-ii",
  "archived_at": "2026-04-16T03:56:07Z",
  "legacy": true,
  "metadata": {
    "title": "Unreleased II",
    "artist": "Ethel Cain",
    "codec": "FLAC",
    "num_tracks": 10,
    "duration_human": "31:44",
    "sampling_rate": "44.1kHz"
  },
  "hosts": {
    "archive_org": {
      "url": "https://archive.org/details/1767676259_unreleased_ii"
    },
    "pomf2_lain_la": {
      "url": "https://pomf2.lain.la/f/quizy7ug.7z"
    },
    "fileditch": {
      "url": "https://fileditchfiles.me/file.php?f=/b69/mZOqdQgSORzLxhsinMG.7z"
    }
  }
}