{
  "id": "9999900-modulation-iv",
  "archived_at": "2026-04-16T03:56:08Z",
  "legacy": true,
  "metadata": {
    "title": "9999900 (Modulation IV)",
    "artist": "Zeffon / Argon Beams / Generated Missiân ZFN / Revenence / Serpentmouth (incomplete as of now)",
    "codec": "FLAC",
    "num_tracks": 0,
    "duration_human": "Unknown",
    "sampling_rate": "Unknown"
  },
  "hosts": {
    "archive_org": {
      "url": "https://archive.org/details/1748610794_zeffon_-_9999900__modulation_iv_"
    },
    "fileditch": {
      "url": "https://fileditchfiles.me/file.php?f=/s23/MbEXKtgBSnCJjoiRdiDP.7z"
    },
    "pomf2_lain_la": {
      "url": "https://pomf2.lain.la/f/fht1w63f.7z"
    }
  }
}