{
  "id": "all-is-full-of-love-1",
  "archived_at": "2026-04-16T03:56:07Z",
  "legacy": true,
  "metadata": {
    "title": "All Is Full Of Love (1)",
    "artist": "Björk",
    "codec": "FLAC",
    "num_tracks": 0,
    "duration_human": "Unknown",
    "sampling_rate": "Unknown"
  },
  "hosts": {
    "archive_org": {
      "url": "https://archive.org/details/1756871855_all_is_full_of_love__1999___1_"
    },
    "fileditch": {
      "url": "https://fileditchfiles.me/file.php?f=/s23/MXJysLYPsMIPPhWjgYFh.7z"
    },
    "catbox": {
      "url": "https://files.catbox.moe/v5lnya.7z"
    },
    "pomf2_lain_la": {
      "url": "https://pomf2.lain.la/f/1qnq214h.7z"
    }
  }
}