{
  "id": "shakamoto-in-a-day",
  "archived_at": "2026-04-16T03:56:08Z",
  "legacy": true,
  "metadata": {
    "title": "shakamoto in a day",
    "artist": "Goreshit",
    "codec": "FLAC",
    "num_tracks": 1,
    "duration_human": "2:51",
    "sampling_rate": "44.1kHz"
  },
  "hosts": {
    "archive_org": {
      "url": "https://archive.org/details/1760537725_shakamoto_in_a_day"
    },
    "fileditch": {
      "url": "https://fileditchfiles.me/file.php?f=/s24/LTeBBujkXOqDECqwehE.7z"
    },
    "pomf2_lain_la": {
      "url": "https://pomf2.lain.la/f/8pbp716h.7z"
    }
  }
}