{
  "id": "the-north-is-another-land",
  "archived_at": "2026-04-16T03:56:07Z",
  "legacy": true,
  "metadata": {
    "title": "The North Is Another Land",
    "artist": "Band of Holy Joy",
    "codec": "FLAC",
    "num_tracks": 8,
    "duration_human": "30:21",
    "sampling_rate": "44.1kHz"
  },
  "hosts": {
    "archive_org": {
      "url": "https://archive.org/details/1759957330_the_north_is_another_land"
    },
    "fileditch": {
      "url": "https://fileditchfiles.me/file.php?f=/s24/wyQpeUPaQpupbMNOJScE.7z"
    },
    "pomf2_lain_la": {
      "url": "https://pomf2.lain.la/f/kw40kld4.7z"
    }
  }
}