{
  "id": "be-like-me-ten-miles-high",
  "archived_at": "2026-04-16T03:56:08Z",
  "legacy": true,
  "metadata": {
    "title": "Be Like Me / Ten Miles High",
    "artist": "Zos Kia",
    "codec": "MP3",
    "num_tracks": 0,
    "duration_human": "Unknown",
    "sampling_rate": "Unknown"
  },
  "hosts": {
    "archive_org": {
      "url": "https://archive.org/details/1752467626_be_like_me_-_ten_miles_high"
    },
    "fileditch": {
      "url": "https://fileditchfiles.me/file.php?f=/s22/IjcgmTtGfTjjBnBcwbY.7z"
    },
    "catbox": {
      "url": "https://files.catbox.moe/fotnac.7z"
    },
    "pomf2_lain_la": {
      "url": "https://pomf2.lain.la/f/p9d7bdvf.7z"
    }
  }
}