{
  "id": "the-vinyl-solution-analog-artifacts-ritual-instrumentals-and-undercover-versions",
  "archived_at": "2026-04-16T03:56:08Z",
  "legacy": true,
  "metadata": {
    "title": "The Vinyl Solution (Analog Artifacts: Ritual Instrumentals and Undercover Versions)",
    "artist": "Radio Werewolf",
    "codec": "FLAC",
    "num_tracks": 0,
    "duration_human": "Unknown",
    "sampling_rate": "Unknown"
  },
  "hosts": {
    "archive_org": {
      "url": "https://archive.org/details/1752328294_the_vinyl_solution_-_analog_artifacts__ritual_inst"
    },
    "fileditch": {
      "url": "https://fileditchfiles.me/file.php?f=/s22/CAkCoZpKLBLLBnuCoRaN.7z"
    },
    "pomf2_lain_la": {
      "url": "https://pomf2.lain.la/f/ak8ujhc.7z"
    }
  }
}