{
  "id": "trist-lonesummer",
  "archived_at": "2026-04-16T03:56:08Z",
  "legacy": true,
  "metadata": {
    "title": "Trist / Lonesummer",
    "artist": "Trist",
    "codec": "FLAC",
    "num_tracks": 0,
    "duration_human": "Unknown",
    "sampling_rate": "Unknown"
  },
  "hosts": {
    "archive_org": {
      "url": "https://archive.org/details/1752467543_trist_-_lonesummer"
    },
    "fileditch": {
      "url": "https://fileditchfiles.me/file.php?f=/s22/EbhCosZnQzLDnICKxlHO.7z"
    },
    "pomf2_lain_la": {
      "url": "https://pomf2.lain.la/f/1cwclj59.7z"
    }
  }
}