{
  "id": "the-prophecy",
  "archived_at": "2026-04-16T03:56:08Z",
  "legacy": true,
  "metadata": {
    "title": "The Prophecy",
    "artist": "Ninja Sex Party",
    "codec": "FLAC",
    "num_tracks": 12,
    "duration_human": "38:40",
    "sampling_rate": "44.1kHz"
  },
  "hosts": {
    "archive_org": {
      "url": "https://archive.org/details/1761359138_the_prophecy"
    },
    "fileditch": {
      "url": "https://fileditchfiles.me/file.php?f=/s24/MJVQAfoLDrZEgvxmesLZ.7z"
    },
    "pomf2_lain_la": {
      "url": "https://pomf2.lain.la/f/y1bykpit.7z"
    }
  }
}