{
  "id": "volume-four-evil-stack-live",
  "archived_at": "2026-04-16T03:56:07Z",
  "legacy": true,
  "metadata": {
    "title": "Volume Four \"Evil Stack Live\"",
    "artist": "Boris",
    "codec": "FLAC",
    "num_tracks": 9,
    "duration_human": "47:16",
    "sampling_rate": "44.1kHz"
  },
  "hosts": {
    "archive_org": {
      "url": "https://archive.org/details/1764487385_volume_four_evil_stack_live"
    },
    "fileditch": {
      "url": "https://fileditchfiles.me/file.php?f=/s24/IIGFFLKSQJYnsNvJlOnn.7z"
    },
    "pomf2_lain_la": {
      "url": "https://pomf2.lain.la/f/aix8h1ud.7z"
    }
  }
}