{
  "id": "dyn-vywjil-nen-jyn-dij-nendindalnen-dyn-lelqit-nen-vaw-qanjiw-tremaalk-lalvunqat-lalvun_06c825531638",
  "fingerprint": "06c8255316381073939524659838f05d57274ab4c0cd6577000ead720027d253",
  "archived_at": "2026-07-11T21:17:11Z",
  "metadata": {
    "title": "dyn vywjil nen jyn dij nendindalnen dyn lelqit nen vaw qanjiw / tremaalk' lalvunqat lalvunqat",
    "artist": "Coffret de Bijoux",
    "year": "2026",
    "codec": "FLAC",
    "num_tracks": 7,
    "duration_seconds": 1963,
    "duration_human": "00:32:43",
    "sampling_rate": "44.1kHz",
    "bit_depth": "16-bit",
    "tracklist": [
      "01 Coffret de Bijoux - nôjnil I∶ prav u",
      "02 Coffret de Bijoux - nôjnil II∶ yvelt, ershan",
      "03 Coffret de Bijoux - nôjnil III∶ ju'n",
      "04 Coffret de Bijoux - nôjnil IV∶ dyn vywjil",
      "05 Coffret de Bijoux - nôjnil I∶ qulpah",
      "06 Coffret de Bijoux - nôjnil II∶ juna dol intablej'",
      "07 Coffret de Bijoux - nôjnil III∶ limana kojn"
    ]
  },
  "hosts": {
    "archive_org": {
      "url": "https://archive.org/details/dyn-vywjil-nen-jyn-dij-nendindalnen-dyn-lelqit-nen-vaw-qanjiw-tremaalk-lalvunqat-lalvun_06c825531638"
    },
    "fileditch": {
      "url": "https://fileditchfiles.st/beta12/120c88742d7710e46e5f/dyn_vywjil_nen_jyn_dij_nendindalnen_dyn_lelqit_nen_vaw_qanjiw.tar"
    }
  }
}