{
  "id": "tee",
  "archived_at": "2026-04-16T03:56:08Z",
  "legacy": true,
  "metadata": {
    "title": "tee",
    "artist": "Maximum Movement Theatre",
    "codec": "FLAC",
    "num_tracks": 1,
    "duration_human": "30:24",
    "sampling_rate": "44.1kHz"
  },
  "hosts": {
    "archive_org": {
      "url": "https://archive.org/details/1761336796_tee"
    },
    "fileditch": {
      "url": "https://fileditchfiles.me/file.php?f=/s24/oxEGkaqyecOfxJVdcAGS.7z"
    },
    "catbox": {
      "url": "https://files.catbox.moe/05uhok.7z"
    },
    "pomf2_lain_la": {
      "url": "https://pomf2.lain.la/f/im3hn5v0.7z"
    }
  }
}