{
  "id": "black-balloons-reprise",
  "archived_at": "2026-04-16T03:56:08Z",
  "legacy": true,
  "metadata": {
    "title": "Black Balloons Reprise",
    "artist": "Flying Lotus",
    "codec": "FLAC",
    "num_tracks": 0,
    "duration_human": "Unknown",
    "sampling_rate": "Unknown"
  },
  "hosts": {
    "archive_org": {
      "url": "https://archive.org/details/1757191343_black_balloons_reprise"
    },
    "fileditch": {
      "url": "https://fileditchfiles.me/file.php?f=/s24/ChwywfEaRjrymssGyWFC.7z"
    },
    "catbox": {
      "url": "https://files.catbox.moe/cnhlub.7z"
    },
    "pomf2_lain_la": {
      "url": "https://pomf2.lain.la/f/qgmg4zdr.7z"
    }
  }
}